{"directed": false, "multigraph": false, "graph": [], "nodes": [{"graph": null, "nnodes": 3, "nedges": 2, "density": 0.6666666666666666, "atomics": "[138, 139, 127]", "group_pop": 3, "init_part_assignment": 0, "D": 1, "R": 2, "id": 0}, {"graph": null, "nnodes": 3, "nedges": 2, "density": 0.6666666666666666, "atomics": "[114, 115, 126]", "group_pop": 3, "init_part_assignment": 0, "D": 2, "R": 1, "id": 1}, {"graph": null, "nnodes": 3, "nedges": 2, "density": 0.6666666666666666, "atomics": "[128, 116, 140]", "group_pop": 3, "init_part_assignment": 0, "D": 2, "R": 1, "id": 2}, {"graph": null, "nnodes": 3, "nedges": 2, "density": 0.6666666666666666, "atomics": "[104, 105, 103]", "group_pop": 3, "init_part_assignment": 7, "D": 2, "R": 1, "id": 3}, {"graph": null, "nnodes": 3, "nedges": 2, "density": 0.6666666666666666, "atomics": "[122, 133, 134]", "group_pop": 3, "init_part_assignment": 2, "D": 2, "R": 1, "id": 4}, {"graph": null, "nnodes": 3, "nedges": 2, "density": 0.6666666666666666, "atomics": "[135, 123, 111]", "group_pop": 3, "init_part_assignment": 11, "D": 3, "R": 0, "id": 5}, {"graph": null, "nnodes": 3, "nedges": 2, "density": 0.6666666666666666, "atomics": "[0, 1, 12]", "group_pop": 3, "init_part_assignment": 1, "D": 2, "R": 1, "id": 6}, {"graph": null, "nnodes": 3, "nedges": 2, "density": 0.6666666666666666, "atomics": "[24, 25, 13]", "group_pop": 3, "init_part_assignment": 1, "D": 0, "R": 3, "id": 7}, {"graph": null, "nnodes": 3, "nedges": 2, "density": 0.6666666666666666, "atomics": "[8, 9, 21]", "group_pop": 3, "init_part_assignment": 3, "D": 3, "R": 0, "id": 8}, {"graph": null, "nnodes": 3, "nedges": 2, "density": 0.6666666666666666, "atomics": "[32, 20, 44]", "group_pop": 3, "init_part_assignment": 7, "D": 2, "R": 1, "id": 9}, {"graph": null, "nnodes": 3, "nedges": 2, "density": 0.6666666666666666, "atomics": "[19, 7, 31]", "group_pop": 3, "init_part_assignment": 4, "D": 2, "R": 1, "id": 10}, {"graph": null, "nnodes": 3, "nedges": 2, "density": 0.6666666666666666, "atomics": "[2, 26, 14]", "group_pop": 3, "init_part_assignment": 4, "D": 2, "R": 1, "id": 11}, {"graph": null, "nnodes": 3, "nedges": 2, "density": 0.6666666666666666, "atomics": "[3, 4, 5]", "group_pop": 3, "init_part_assignment": 4, "D": 3, "R": 0, "id": 12}, {"graph": null, "nnodes": 3, "nedges": 2, "density": 0.6666666666666666, "atomics": "[107, 83, 95]", "group_pop": 3, "init_part_assignment": 5, "D": 0, "R": 3, "id": 13}, {"graph": null, "nnodes": 3, "nedges": 2, "density": 0.6666666666666666, "atomics": "[16, 17, 29]", "group_pop": 3, "init_part_assignment": 8, "D": 2, "R": 1, "id": 14}, {"graph": null, "nnodes": 3, "nedges": 2, "density": 0.6666666666666666, "atomics": "[112, 113, 124]", "group_pop": 3, "init_part_assignment": 11, "D": 2, "R": 1, "id": 15}, {"graph": null, "nnodes": 3, "nedges": 2, "density": 0.6666666666666666, "atomics": "[121, 109, 110]", "group_pop": 3, "init_part_assignment": 2, "D": 2, "R": 1, "id": 16}, {"graph": null, "nnodes": 3, "nedges": 2, "density": 0.6666666666666666, "atomics": "[120, 132, 108]", "group_pop": 3, "init_part_assignment": 2, "D": 0, "R": 3, "id": 17}, {"graph": null, "nnodes": 3, "nedges": 2, "density": 0.6666666666666666, "atomics": "[136, 137, 125]", "group_pop": 3, "init_part_assignment": 0, "D": 0, "R": 3, "id": 18}, {"graph": null, "nnodes": 3, "nedges": 2, "density": 0.6666666666666666, "atomics": "[10, 34, 22]", "group_pop": 3, "init_part_assignment": 3, "D": 2, "R": 1, "id": 19}, {"graph": null, "nnodes": 3, "nedges": 2, "density": 0.6666666666666666, "atomics": "[129, 141, 142]", "group_pop": 3, "init_part_assignment": 5, "D": 2, "R": 1, "id": 20}, {"graph": null, "nnodes": 3, "nedges": 2, "density": 0.6666666666666666, "atomics": "[88, 89, 87]", "group_pop": 3, "init_part_assignment": 10, "D": 2, "R": 1, "id": 21}, {"graph": null, "nnodes": 3, "nedges": 2, "density": 0.6666666666666666, "atomics": "[99, 100, 101]", "group_pop": 3, "init_part_assignment": 11, "D": 2, "R": 1, "id": 22}, {"graph": null, "nnodes": 3, "nedges": 2, "density": 0.6666666666666666, "atomics": "[90, 91, 102]", "group_pop": 3, "init_part_assignment": 11, "D": 2, "R": 1, "id": 23}, {"graph": null, "nnodes": 3, "nedges": 2, "density": 0.6666666666666666, "atomics": "[80, 92, 68]", "group_pop": 3, "init_part_assignment": 7, "D": 3, "R": 0, "id": 24}, {"graph": null, "nnodes": 3, "nedges": 2, "density": 0.6666666666666666, "atomics": "[48, 49, 60]", "group_pop": 3, "init_part_assignment": 1, "D": 2, "R": 1, "id": 25}, {"graph": null, "nnodes": 3, "nedges": 2, "density": 0.6666666666666666, "atomics": "[36, 37, 38]", "group_pop": 3, "init_part_assignment": 1, "D": 2, "R": 1, "id": 26}, {"graph": null, "nnodes": 3, "nedges": 2, "density": 0.6666666666666666, "atomics": "[96, 97, 98]", "group_pop": 3, "init_part_assignment": 2, "D": 2, "R": 1, "id": 27}, {"graph": null, "nnodes": 3, "nedges": 2, "density": 0.6666666666666666, "atomics": "[84, 85, 86]", "group_pop": 3, "init_part_assignment": 10, "D": 2, "R": 1, "id": 28}, {"graph": null, "nnodes": 3, "nedges": 2, "density": 0.6666666666666666, "atomics": "[18, 6, 30]", "group_pop": 3, "init_part_assignment": 4, "D": 0, "R": 3, "id": 29}, {"graph": null, "nnodes": 3, "nedges": 2, "density": 0.6666666666666666, "atomics": "[27, 28, 15]", "group_pop": 3, "init_part_assignment": 8, "D": 2, "R": 1, "id": 30}, {"graph": null, "nnodes": 3, "nedges": 2, "density": 0.6666666666666666, "atomics": "[40, 41, 39]", "group_pop": 3, "init_part_assignment": 8, "D": 2, "R": 1, "id": 31}, {"graph": null, "nnodes": 3, "nedges": 2, "density": 0.6666666666666666, "atomics": "[72, 73, 74]", "group_pop": 3, "init_part_assignment": 10, "D": 1, "R": 2, "id": 32}, {"graph": null, "nnodes": 3, "nedges": 2, "density": 0.6666666666666666, "atomics": "[50, 61, 62]", "group_pop": 3, "init_part_assignment": 9, "D": 3, "R": 0, "id": 33}, {"graph": null, "nnodes": 3, "nedges": 2, "density": 0.6666666666666666, "atomics": "[75, 51, 63]", "group_pop": 3, "init_part_assignment": 9, "D": 2, "R": 1, "id": 34}, {"graph": null, "nnodes": 3, "nedges": 2, "density": 0.6666666666666666, "atomics": "[76, 77, 78]", "group_pop": 3, "init_part_assignment": 10, "D": 2, "R": 1, "id": 35}, {"graph": null, "nnodes": 3, "nedges": 2, "density": 0.6666666666666666, "atomics": "[130, 117, 118]", "group_pop": 3, "init_part_assignment": 5, "D": 2, "R": 1, "id": 36}, {"graph": null, "nnodes": 3, "nedges": 2, "density": 0.6666666666666666, "atomics": "[143, 131, 119]", "group_pop": 3, "init_part_assignment": 5, "D": 2, "R": 1, "id": 37}, {"graph": null, "nnodes": 3, "nedges": 2, "density": 0.6666666666666666, "atomics": "[66, 67, 79]", "group_pop": 3, "init_part_assignment": 9, "D": 2, "R": 1, "id": 38}, {"graph": null, "nnodes": 3, "nedges": 2, "density": 0.6666666666666666, "atomics": "[11, 35, 23]", "group_pop": 3, "init_part_assignment": 3, "D": 2, "R": 1, "id": 39}, {"graph": null, "nnodes": 3, "nedges": 2, "density": 0.6666666666666666, "atomics": "[56, 43, 55]", "group_pop": 3, "init_part_assignment": 7, "D": 0, "R": 3, "id": 40}, {"graph": null, "nnodes": 3, "nedges": 2, "density": 0.6666666666666666, "atomics": "[57, 45, 33]", "group_pop": 3, "init_part_assignment": 6, "D": 2, "R": 1, "id": 41}, {"graph": null, "nnodes": 3, "nedges": 2, "density": 0.6666666666666666, "atomics": "[106, 82, 94]", "group_pop": 3, "init_part_assignment": 6, "D": 2, "R": 1, "id": 42}, {"graph": null, "nnodes": 3, "nedges": 2, "density": 0.6666666666666666, "atomics": "[64, 65, 52]", "group_pop": 3, "init_part_assignment": 9, "D": 2, "R": 1, "id": 43}, {"graph": null, "nnodes": 3, "nedges": 2, "density": 0.6666666666666666, "atomics": "[42, 53, 54]", "group_pop": 3, "init_part_assignment": 8, "D": 2, "R": 1, "id": 44}, {"graph": null, "nnodes": 3, "nedges": 2, "density": 0.6666666666666666, "atomics": "[81, 93, 69]", "group_pop": 3, "init_part_assignment": 6, "D": 1, "R": 2, "id": 45}, {"graph": null, "nnodes": 3, "nedges": 2, "density": 0.6666666666666666, "atomics": "[59, 47, 71]", "group_pop": 3, "init_part_assignment": 3, "D": 2, "R": 1, "id": 46}, {"graph": null, "nnodes": 3, "nedges": 2, "density": 0.6666666666666666, "atomics": "[46, 58, 70]", "group_pop": 3, "init_part_assignment": 6, "D": 2, "R": 1, "id": 47}], "adjacency": [[{"weight": 3, "random_weight": 0.980006714063022, "id": 1}, {"weight": 2, "random_weight": 0.5968707426670371, "id": 2}, {"weight": 1, "random_weight": 0.6299957031727798, "id": 18}], [{"weight": 3, "random_weight": 0.980006714063022, "id": 0}, {"weight": 1, "random_weight": 0.041027408109194585, "id": 2}, {"weight": 1, "random_weight": 0.7421124012354694, "id": 3}, {"weight": 1, "random_weight": 0.638901687539284, "id": 15}, {"weight": 1, "random_weight": 0.045848518834098795, "id": 18}, {"weight": 1, "random_weight": 0.8318780080473205, "id": 23}], [{"weight": 2, "random_weight": 0.5968707426670371, "id": 0}, {"weight": 1, "random_weight": 0.041027408109194585, "id": 1}, {"weight": 1, "random_weight": 0.3907633781006401, "id": 3}, {"weight": 2, "random_weight": 0.8653718769859654, "id": 20}, {"weight": 1, "random_weight": 0.8395222534758674, "id": 36}], [{"weight": 1, "random_weight": 0.7421124012354694, "id": 1}, {"weight": 1, "random_weight": 0.3907633781006401, "id": 2}, {"weight": 2, "random_weight": 0.988309654539652, "id": 23}, {"weight": 1, "random_weight": 0.7747067413693984, "id": 24}, {"weight": 1, "random_weight": 0.4815074360596989, "id": 36}, {"weight": 1, "random_weight": 0.9772122377213595, "id": 42}, {"weight": 1, "random_weight": 0.48862587286617687, "id": 45}], [{"weight": 2, "random_weight": 0.6116078821949744, "id": 5}, {"weight": 3, "random_weight": 0.28030133182064454, "id": 16}, {"weight": 1, "random_weight": 0.41266800800896386, "id": 17}], [{"weight": 2, "random_weight": 0.6116078821949744, "id": 4}, {"weight": 2, "random_weight": 0.20437220918074717, "id": 15}, {"weight": 1, "random_weight": 0.9285748164691389, "id": 16}, {"weight": 1, "random_weight": 0.9917091320745348, "id": 18}, {"weight": 1, "random_weight": 0.25072130997239195, "id": 22}], [{"weight": 3, "random_weight": 0.5067746412597525, "id": 7}, {"weight": 1, "random_weight": 0.8839687331395121, "id": 11}], [{"weight": 3, "random_weight": 0.5067746412597525, "id": 6}, {"weight": 2, "random_weight": 0.801697683361576, "id": 11}, {"weight": 2, "random_weight": 0.7030727862407797, "id": 26}], [{"weight": 2, "random_weight": 0.8487057215841131, "id": 9}, {"weight": 1, "random_weight": 0.6842024999744015, "id": 10}, {"weight": 2, "random_weight": 0.3154010029911192, "id": 19}, {"weight": 1, "random_weight": 0.43580633511426636, "id": 41}], [{"weight": 2, "random_weight": 0.8487057215841131, "id": 8}, {"weight": 2, "random_weight": 0.853253010007361, "id": 10}, {"weight": 2, "random_weight": 0.19567162416562756, "id": 40}, {"weight": 2, "random_weight": 0.8995408463983604, "id": 41}], [{"weight": 1, "random_weight": 0.6842024999744015, "id": 8}, {"weight": 2, "random_weight": 0.853253010007361, "id": 9}, {"weight": 3, "random_weight": 0.3022372043774407, "id": 29}, {"weight": 1, "random_weight": 0.5841250312847122, "id": 40}], [{"weight": 1, "random_weight": 0.8839687331395121, "id": 6}, {"weight": 2, "random_weight": 0.801697683361576, "id": 7}, {"weight": 1, "random_weight": 0.3915959651010149, "id": 12}, {"weight": 1, "random_weight": 0.9955569540426994, "id": 26}, {"weight": 2, "random_weight": 0.8246056120890696, "id": 30}], [{"weight": 1, "random_weight": 0.3915959651010149, "id": 11}, {"weight": 2, "random_weight": 0.8701642878838847, "id": 14}, {"weight": 1, "random_weight": 0.23684778584295152, "id": 29}, {"weight": 1, "random_weight": 0.8469600599943512, "id": 30}], [{"weight": 1, "random_weight": 0.37976639089405895, "id": 37}, {"weight": 3, "random_weight": 0.22049722397788452, "id": 42}, {"weight": 1, "random_weight": 0.7662124994759745, "id": 46}], [{"weight": 2, "random_weight": 0.8701642878838847, "id": 12}, {"weight": 2, "random_weight": 0.7617013606400045, "id": 29}, {"weight": 3, "random_weight": 0.5000072390144332, "id": 30}, {"weight": 1, "random_weight": 0.37568369967604665, "id": 31}], [{"weight": 1, "random_weight": 0.638901687539284, "id": 1}, {"weight": 2, "random_weight": 0.20437220918074717, "id": 5}, {"weight": 3, "random_weight": 0.5442884209912144, "id": 18}, {"weight": 2, "random_weight": 0.5629579728604607, "id": 22}], [{"weight": 3, "random_weight": 0.28030133182064454, "id": 4}, {"weight": 1, "random_weight": 0.9285748164691389, "id": 5}, {"weight": 2, "random_weight": 0.36358943591083226, "id": 17}, {"weight": 2, "random_weight": 0.028648000356794157, "id": 27}], [{"weight": 1, "random_weight": 0.41266800800896386, "id": 4}, {"weight": 2, "random_weight": 0.36358943591083226, "id": 16}, {"weight": 1, "random_weight": 0.5408349684773857, "id": 27}], [{"weight": 1, "random_weight": 0.6299957031727798, "id": 0}, {"weight": 1, "random_weight": 0.045848518834098795, "id": 1}, {"weight": 1, "random_weight": 0.9917091320745348, "id": 5}, {"weight": 3, "random_weight": 0.5442884209912144, "id": 15}], [{"weight": 2, "random_weight": 0.3154010029911192, "id": 8}, {"weight": 3, "random_weight": 0.02406090510839254, "id": 39}, {"weight": 1, "random_weight": 0.756116031395569, "id": 41}, {"weight": 1, "random_weight": 0.9585044898988225, "id": 47}], [{"weight": 2, "random_weight": 0.8653718769859654, "id": 2}, {"weight": 3, "random_weight": 0.11005512865386124, "id": 36}, {"weight": 1, "random_weight": 0.4982859265127778, "id": 37}], [{"weight": 3, "random_weight": 0.18532866920410096, "id": 22}, {"weight": 1, "random_weight": 0.5469498871829701, "id": 23}, {"weight": 1, "random_weight": 0.9580674449113932, "id": 28}, {"weight": 1, "random_weight": 0.8215676696118487, "id": 34}, {"weight": 2, "random_weight": 0.5819631706355836, "id": 35}], [{"weight": 1, "random_weight": 0.25072130997239195, "id": 5}, {"weight": 2, "random_weight": 0.5629579728604607, "id": 15}, {"weight": 3, "random_weight": 0.18532866920410096, "id": 21}, {"weight": 1, "random_weight": 0.22748145938747633, "id": 23}, {"weight": 1, "random_weight": 0.2442889422998632, "id": 27}], [{"weight": 1, "random_weight": 0.8318780080473205, "id": 1}, {"weight": 2, "random_weight": 0.988309654539652, "id": 3}, {"weight": 1, "random_weight": 0.5469498871829701, "id": 21}, {"weight": 1, "random_weight": 0.22748145938747633, "id": 22}, {"weight": 1, "random_weight": 0.6701804541238999, "id": 24}, {"weight": 1, "random_weight": 0.7976066135023248, "id": 35}, {"weight": 1, "random_weight": 0.4988734691605904, "id": 38}], [{"weight": 1, "random_weight": 0.7747067413693984, "id": 3}, {"weight": 1, "random_weight": 0.6701804541238999, "id": 23}, {"weight": 2, "random_weight": 0.6247021726522349, "id": 38}, {"weight": 1, "random_weight": 0.2043759332976297, "id": 40}, {"weight": 3, "random_weight": 0.4324042144094167, "id": 45}], [{"weight": 2, "random_weight": 0.5736255581000506, "id": 26}, {"weight": 1, "random_weight": 0.621124699538959, "id": 32}, {"weight": 3, "random_weight": 0.9193150146565541, "id": 33}], [{"weight": 2, "random_weight": 0.7030727862407797, "id": 7}, {"weight": 1, "random_weight": 0.9955569540426994, "id": 11}, {"weight": 2, "random_weight": 0.5736255581000506, "id": 25}, {"weight": 1, "random_weight": 0.7626387238649975, "id": 31}, {"weight": 1, "random_weight": 0.8377499214186568, "id": 33}], [{"weight": 2, "random_weight": 0.028648000356794157, "id": 16}, {"weight": 1, "random_weight": 0.5408349684773857, "id": 17}, {"weight": 1, "random_weight": 0.2442889422998632, "id": 22}, {"weight": 3, "random_weight": 0.8972896671498083, "id": 28}], [{"weight": 1, "random_weight": 0.9580674449113932, "id": 21}, {"weight": 3, "random_weight": 0.8972896671498083, "id": 27}, {"weight": 3, "random_weight": 0.5073581698604642, "id": 32}], [{"weight": 3, "random_weight": 0.3022372043774407, "id": 10}, {"weight": 1, "random_weight": 0.23684778584295152, "id": 12}, {"weight": 2, "random_weight": 0.7617013606400045, "id": 14}, {"weight": 1, "random_weight": 0.006047864096859867, "id": 44}], [{"weight": 2, "random_weight": 0.8246056120890696, "id": 11}, {"weight": 1, "random_weight": 0.8469600599943512, "id": 12}, {"weight": 3, "random_weight": 0.5000072390144332, "id": 14}, {"weight": 2, "random_weight": 0.6875809017649009, "id": 31}], [{"weight": 1, "random_weight": 0.37568369967604665, "id": 14}, {"weight": 1, "random_weight": 0.7626387238649975, "id": 26}, {"weight": 2, "random_weight": 0.6875809017649009, "id": 30}, {"weight": 1, "random_weight": 0.6925336345041849, "id": 34}, {"weight": 1, "random_weight": 0.7508603472001003, "id": 43}, {"weight": 2, "random_weight": 0.2934141117058088, "id": 44}], [{"weight": 1, "random_weight": 0.621124699538959, "id": 25}, {"weight": 3, "random_weight": 0.5073581698604642, "id": 28}, {"weight": 2, "random_weight": 0.8993557356793597, "id": 33}, {"weight": 1, "random_weight": 0.6330080094873609, "id": 34}], [{"weight": 3, "random_weight": 0.9193150146565541, "id": 25}, {"weight": 1, "random_weight": 0.8377499214186568, "id": 26}, {"weight": 2, "random_weight": 0.8993557356793597, "id": 32}, {"weight": 2, "random_weight": 0.6495243139838116, "id": 34}], [{"weight": 1, "random_weight": 0.8215676696118487, "id": 21}, {"weight": 1, "random_weight": 0.6925336345041849, "id": 31}, {"weight": 1, "random_weight": 0.6330080094873609, "id": 32}, {"weight": 2, "random_weight": 0.6495243139838116, "id": 33}, {"weight": 1, "random_weight": 0.780129520159214, "id": 35}, {"weight": 2, "random_weight": 0.38177976291057747, "id": 43}], [{"weight": 2, "random_weight": 0.5819631706355836, "id": 21}, {"weight": 1, "random_weight": 0.7976066135023248, "id": 23}, {"weight": 1, "random_weight": 0.780129520159214, "id": 34}, {"weight": 2, "random_weight": 0.7417581323034679, "id": 38}, {"weight": 2, "random_weight": 0.1139923931629131, "id": 43}], [{"weight": 1, "random_weight": 0.8395222534758674, "id": 2}, {"weight": 1, "random_weight": 0.4815074360596989, "id": 3}, {"weight": 3, "random_weight": 0.11005512865386124, "id": 20}, {"weight": 2, "random_weight": 0.13643942665620623, "id": 37}, {"weight": 1, "random_weight": 0.6940144985844626, "id": 42}], [{"weight": 1, "random_weight": 0.37976639089405895, "id": 13}, {"weight": 1, "random_weight": 0.4982859265127778, "id": 20}, {"weight": 2, "random_weight": 0.13643942665620623, "id": 36}], [{"weight": 1, "random_weight": 0.4988734691605904, "id": 23}, {"weight": 2, "random_weight": 0.6247021726522349, "id": 24}, {"weight": 2, "random_weight": 0.7417581323034679, "id": 35}, {"weight": 1, "random_weight": 0.9737728289980375, "id": 40}, {"weight": 1, "random_weight": 0.0033214171989236485, "id": 43}, {"weight": 1, "random_weight": 0.9711751528767604, "id": 44}], [{"weight": 3, "random_weight": 0.02406090510839254, "id": 19}, {"weight": 1, "random_weight": 0.28534051889085943, "id": 46}], [{"weight": 2, "random_weight": 0.19567162416562756, "id": 9}, {"weight": 1, "random_weight": 0.5841250312847122, "id": 10}, {"weight": 1, "random_weight": 0.2043759332976297, "id": 24}, {"weight": 1, "random_weight": 0.9737728289980375, "id": 38}, {"weight": 1, "random_weight": 0.22858948260345524, "id": 41}, {"weight": 2, "random_weight": 0.11443600147815514, "id": 44}], [{"weight": 1, "random_weight": 0.43580633511426636, "id": 8}, {"weight": 2, "random_weight": 0.8995408463983604, "id": 9}, {"weight": 1, "random_weight": 0.756116031395569, "id": 19}, {"weight": 1, "random_weight": 0.22858948260345524, "id": 40}, {"weight": 1, "random_weight": 0.30796728709198395, "id": 45}, {"weight": 2, "random_weight": 0.6644017010553646, "id": 47}], [{"weight": 1, "random_weight": 0.9772122377213595, "id": 3}, {"weight": 3, "random_weight": 0.22049722397788452, "id": 13}, {"weight": 1, "random_weight": 0.6940144985844626, "id": 36}, {"weight": 2, "random_weight": 0.4977748209657542, "id": 45}, {"weight": 1, "random_weight": 0.7412053274194405, "id": 47}], [{"weight": 1, "random_weight": 0.7508603472001003, "id": 31}, {"weight": 2, "random_weight": 0.38177976291057747, "id": 34}, {"weight": 2, "random_weight": 0.1139923931629131, "id": 35}, {"weight": 1, "random_weight": 0.0033214171989236485, "id": 38}, {"weight": 2, "random_weight": 0.045577656909711495, "id": 44}], [{"weight": 1, "random_weight": 0.006047864096859867, "id": 29}, {"weight": 2, "random_weight": 0.2934141117058088, "id": 31}, {"weight": 1, "random_weight": 0.9711751528767604, "id": 38}, {"weight": 2, "random_weight": 0.11443600147815514, "id": 40}, {"weight": 2, "random_weight": 0.045577656909711495, "id": 43}], [{"weight": 1, "random_weight": 0.48862587286617687, "id": 3}, {"weight": 3, "random_weight": 0.4324042144094167, "id": 24}, {"weight": 1, "random_weight": 0.30796728709198395, "id": 41}, {"weight": 2, "random_weight": 0.4977748209657542, "id": 42}, {"weight": 1, "random_weight": 0.1873830176897442, "id": 47}], [{"weight": 1, "random_weight": 0.7662124994759745, "id": 13}, {"weight": 1, "random_weight": 0.28534051889085943, "id": 39}, {"weight": 3, "random_weight": 0.3839524499665392, "id": 47}], [{"weight": 1, "random_weight": 0.9585044898988225, "id": 19}, {"weight": 2, "random_weight": 0.6644017010553646, "id": 41}, {"weight": 1, "random_weight": 0.7412053274194405, "id": 42}, {"weight": 1, "random_weight": 0.1873830176897442, "id": 45}, {"weight": 3, "random_weight": 0.3839524499665392, "id": 46}]]}