{"directed": false, "multigraph": false, "graph": [], "nodes": [{"graph": null, "nnodes": 4, "nedges": 3, "density": 0.5, "atomics": "[130, 107, 131, 119]", "group_pop": 4, "init_part_assignment": 0, "D": 2, "R": 2, "id": 0}, {"graph": null, "nnodes": 4, "nedges": 3, "density": 0.5, "atomics": "[140, 141, 142, 143]", "group_pop": 4, "init_part_assignment": 0, "D": 4, "R": 0, "id": 1}, {"graph": null, "nnodes": 4, "nedges": 3, "density": 0.5, "atomics": "[0, 1, 2, 12]", "group_pop": 4, "init_part_assignment": 1, "D": 2, "R": 2, "id": 2}, {"graph": null, "nnodes": 4, "nedges": 3, "density": 0.5, "atomics": "[3, 4, 14, 15]", "group_pop": 4, "init_part_assignment": 1, "D": 4, "R": 0, "id": 3}, {"graph": null, "nnodes": 4, "nedges": 3, "density": 0.5, "atomics": "[136, 113, 137, 125]", "group_pop": 4, "init_part_assignment": 11, "D": 0, "R": 4, "id": 4}, {"graph": null, "nnodes": 4, "nedges": 3, "density": 0.5, "atomics": "[104, 114, 102, 103]", "group_pop": 4, "init_part_assignment": 11, "D": 2, "R": 2, "id": 5}, {"graph": null, "nnodes": 4, "nedges": 4, "density": 0.6666666666666666, "atomics": "[88, 89, 100, 101]", "group_pop": 4, "init_part_assignment": 9, "D": 2, "R": 2, "id": 6}, {"graph": null, "nnodes": 4, "nedges": 3, "density": 0.5, "atomics": "[16, 17, 18, 5]", "group_pop": 4, "init_part_assignment": 1, "D": 2, "R": 2, "id": 7}, {"graph": null, "nnodes": 4, "nedges": 3, "density": 0.5, "atomics": "[122, 134, 110, 135]", "group_pop": 4, "init_part_assignment": 4, "D": 3, "R": 1, "id": 8}, {"graph": null, "nnodes": 4, "nedges": 3, "density": 0.5, "atomics": "[121, 132, 109, 133]", "group_pop": 4, "init_part_assignment": 3, "D": 2, "R": 2, "id": 9}, {"graph": null, "nnodes": 4, "nedges": 4, "density": 0.6666666666666666, "atomics": "[112, 123, 124, 111]", "group_pop": 4, "init_part_assignment": 4, "D": 4, "R": 0, "id": 10}, {"graph": null, "nnodes": 4, "nedges": 4, "density": 0.6666666666666666, "atomics": "[138, 139, 126, 127]", "group_pop": 4, "init_part_assignment": 0, "D": 2, "R": 2, "id": 11}, {"graph": null, "nnodes": 4, "nedges": 4, "density": 0.6666666666666666, "atomics": "[57, 58, 45, 46]", "group_pop": 4, "init_part_assignment": 8, "D": 4, "R": 0, "id": 12}, {"graph": null, "nnodes": 4, "nedges": 3, "density": 0.5, "atomics": "[59, 47, 70, 71]", "group_pop": 4, "init_part_assignment": 7, "D": 2, "R": 2, "id": 13}, {"graph": null, "nnodes": 4, "nedges": 4, "density": 0.6666666666666666, "atomics": "[82, 83, 94, 95]", "group_pop": 4, "init_part_assignment": 7, "D": 2, "R": 2, "id": 14}, {"graph": null, "nnodes": 4, "nedges": 4, "density": 0.6666666666666666, "atomics": "[90, 91, 78, 79]", "group_pop": 4, "init_part_assignment": 11, "D": 2, "R": 2, "id": 15}, {"graph": null, "nnodes": 4, "nedges": 3, "density": 0.5, "atomics": "[72, 73, 85, 86]", "group_pop": 4, "init_part_assignment": 3, "D": 2, "R": 2, "id": 16}, {"graph": null, "nnodes": 4, "nedges": 3, "density": 0.5, "atomics": "[97, 98, 99, 87]", "group_pop": 4, "init_part_assignment": 4, "D": 3, "R": 1, "id": 17}, {"graph": null, "nnodes": 4, "nedges": 3, "density": 0.5, "atomics": "[8, 9, 10, 11]", "group_pop": 4, "init_part_assignment": 5, "D": 4, "R": 0, "id": 18}, {"graph": null, "nnodes": 4, "nedges": 3, "density": 0.5, "atomics": "[19, 7, 6, 31]", "group_pop": 4, "init_part_assignment": 5, "D": 2, "R": 2, "id": 19}, {"graph": null, "nnodes": 4, "nedges": 3, "density": 0.5, "atomics": "[128, 129, 115, 116]", "group_pop": 4, "init_part_assignment": 10, "D": 2, "R": 2, "id": 20}, {"graph": null, "nnodes": 4, "nedges": 3, "density": 0.5, "atomics": "[27, 28, 29, 30]", "group_pop": 4, "init_part_assignment": 2, "D": 2, "R": 2, "id": 21}, {"graph": null, "nnodes": 4, "nedges": 3, "density": 0.5, "atomics": "[24, 48, 36, 60]", "group_pop": 4, "init_part_assignment": 6, "D": 2, "R": 2, "id": 22}, {"graph": null, "nnodes": 4, "nedges": 4, "density": 0.6666666666666666, "atomics": "[34, 35, 22, 23]", "group_pop": 4, "init_part_assignment": 7, "D": 2, "R": 2, "id": 23}, {"graph": null, "nnodes": 4, "nedges": 4, "density": 0.6666666666666666, "atomics": "[105, 106, 117, 118]", "group_pop": 4, "init_part_assignment": 10, "D": 2, "R": 2, "id": 24}, {"graph": null, "nnodes": 4, "nedges": 3, "density": 0.5, "atomics": "[25, 26, 37, 13]", "group_pop": 4, "init_part_assignment": 2, "D": 2, "R": 2, "id": 25}, {"graph": null, "nnodes": 4, "nedges": 3, "density": 0.5, "atomics": "[41, 42, 43, 55]", "group_pop": 4, "init_part_assignment": 8, "D": 1, "R": 3, "id": 26}, {"graph": null, "nnodes": 4, "nedges": 3, "density": 0.5, "atomics": "[66, 67, 53, 54]", "group_pop": 4, "init_part_assignment": 9, "D": 3, "R": 1, "id": 27}, {"graph": null, "nnodes": 4, "nedges": 4, "density": 0.6666666666666666, "atomics": "[74, 75, 62, 63]", "group_pop": 4, "init_part_assignment": 6, "D": 2, "R": 2, "id": 28}, {"graph": null, "nnodes": 4, "nedges": 4, "density": 0.6666666666666666, "atomics": "[64, 65, 76, 77]", "group_pop": 4, "init_part_assignment": 9, "D": 2, "R": 2, "id": 29}, {"graph": null, "nnodes": 4, "nedges": 4, "density": 0.6666666666666666, "atomics": "[32, 33, 20, 21]", "group_pop": 4, "init_part_assignment": 5, "D": 2, "R": 2, "id": 30}, {"graph": null, "nnodes": 4, "nedges": 3, "density": 0.5, "atomics": "[120, 108, 96, 84]", "group_pop": 4, "init_part_assignment": 3, "D": 2, "R": 2, "id": 31}, {"graph": null, "nnodes": 4, "nedges": 3, "density": 0.5, "atomics": "[56, 44, 69, 68]", "group_pop": 4, "init_part_assignment": 8, "D": 3, "R": 1, "id": 32}, {"graph": null, "nnodes": 4, "nedges": 4, "density": 0.6666666666666666, "atomics": "[80, 81, 92, 93]", "group_pop": 4, "init_part_assignment": 10, "D": 2, "R": 2, "id": 33}, {"graph": null, "nnodes": 4, "nedges": 3, "density": 0.5, "atomics": "[49, 50, 51, 61]", "group_pop": 4, "init_part_assignment": 6, "D": 3, "R": 1, "id": 34}, {"graph": null, "nnodes": 4, "nedges": 3, "density": 0.5, "atomics": "[40, 52, 38, 39]", "group_pop": 4, "init_part_assignment": 2, "D": 4, "R": 0, "id": 35}], "adjacency": [[{"weight": 2, "random_weight": 0.0056874889433548015, "id": 1}, {"weight": 1, "random_weight": 0.7829019859626253, "id": 14}, {"weight": 1, "random_weight": 0.26315996824837773, "id": 20}, {"weight": 3, "random_weight": 0.6582864993963016, "id": 24}], [{"weight": 2, "random_weight": 0.0056874889433548015, "id": 0}, {"weight": 1, "random_weight": 0.07353583413830778, "id": 11}, {"weight": 2, "random_weight": 0.39955796829548706, "id": 20}], [{"weight": 2, "random_weight": 0.48532346909400637, "id": 3}, {"weight": 1, "random_weight": 0.9035713597714097, "id": 22}, {"weight": 2, "random_weight": 0.5049388417188215, "id": 25}], [{"weight": 2, "random_weight": 0.48532346909400637, "id": 2}, {"weight": 3, "random_weight": 0.08560580682118102, "id": 7}, {"weight": 1, "random_weight": 0.03590374323551693, "id": 21}, {"weight": 2, "random_weight": 0.6844042563391108, "id": 25}], [{"weight": 1, "random_weight": 0.04068939042539432, "id": 5}, {"weight": 1, "random_weight": 0.5783935876104371, "id": 6}, {"weight": 1, "random_weight": 0.28804631243747747, "id": 8}, {"weight": 3, "random_weight": 0.7357317920792218, "id": 10}, {"weight": 2, "random_weight": 0.7199393819035077, "id": 11}], [{"weight": 1, "random_weight": 0.04068939042539432, "id": 4}, {"weight": 1, "random_weight": 0.7559454508264525, "id": 6}, {"weight": 1, "random_weight": 0.7169693901917068, "id": 11}, {"weight": 2, "random_weight": 0.27805790160733934, "id": 15}, {"weight": 3, "random_weight": 0.5643316957933392, "id": 20}, {"weight": 1, "random_weight": 0.6711779246743013, "id": 24}, {"weight": 1, "random_weight": 0.5108609937833836, "id": 33}], [{"weight": 1, "random_weight": 0.5783935876104371, "id": 4}, {"weight": 1, "random_weight": 0.7559454508264525, "id": 5}, {"weight": 1, "random_weight": 0.4431532208094313, "id": 10}, {"weight": 1, "random_weight": 0.7906143108875033, "id": 15}, {"weight": 2, "random_weight": 0.832166193067156, "id": 17}, {"weight": 2, "random_weight": 0.8771296230065246, "id": 29}], [{"weight": 3, "random_weight": 0.08560580682118102, "id": 3}, {"weight": 3, "random_weight": 0.9485402788417032, "id": 19}, {"weight": 3, "random_weight": 0.9461915250725256, "id": 21}], [{"weight": 1, "random_weight": 0.28804631243747747, "id": 4}, {"weight": 3, "random_weight": 0.6912057805946524, "id": 9}, {"weight": 3, "random_weight": 0.2819974994994644, "id": 10}, {"weight": 1, "random_weight": 0.4706861807635312, "id": 17}], [{"weight": 3, "random_weight": 0.6912057805946524, "id": 8}, {"weight": 1, "random_weight": 0.070327472816895, "id": 17}, {"weight": 3, "random_weight": 0.141721576501454, "id": 31}], [{"weight": 3, "random_weight": 0.7357317920792218, "id": 4}, {"weight": 1, "random_weight": 0.4431532208094313, "id": 6}, {"weight": 3, "random_weight": 0.2819974994994644, "id": 8}, {"weight": 1, "random_weight": 0.9882719149022531, "id": 17}], [{"weight": 1, "random_weight": 0.07353583413830778, "id": 1}, {"weight": 2, "random_weight": 0.7199393819035077, "id": 4}, {"weight": 1, "random_weight": 0.7169693901917068, "id": 5}, {"weight": 2, "random_weight": 0.24062754124659058, "id": 20}], [{"weight": 3, "random_weight": 0.8965213339346443, "id": 13}, {"weight": 1, "random_weight": 0.8780617888059121, "id": 23}, {"weight": 1, "random_weight": 0.8748375371843705, "id": 30}, {"weight": 3, "random_weight": 0.020320598347317365, "id": 32}], [{"weight": 3, "random_weight": 0.8965213339346443, "id": 12}, {"weight": 2, "random_weight": 0.08980238257751949, "id": 14}, {"weight": 1, "random_weight": 0.3491118493690002, "id": 23}, {"weight": 1, "random_weight": 0.7710053811101878, "id": 32}], [{"weight": 1, "random_weight": 0.7829019859626253, "id": 0}, {"weight": 2, "random_weight": 0.08980238257751949, "id": 13}, {"weight": 1, "random_weight": 0.09917156377274161, "id": 24}, {"weight": 2, "random_weight": 0.946408708218907, "id": 33}], [{"weight": 2, "random_weight": 0.27805790160733934, "id": 5}, {"weight": 1, "random_weight": 0.7906143108875033, "id": 6}, {"weight": 2, "random_weight": 0.9844034943365504, "id": 27}, {"weight": 1, "random_weight": 0.9442834975864549, "id": 29}, {"weight": 2, "random_weight": 0.6718142979905276, "id": 33}], [{"weight": 3, "random_weight": 0.31572201321166504, "id": 17}, {"weight": 1, "random_weight": 0.710141350275285, "id": 22}, {"weight": 2, "random_weight": 0.5718937828036534, "id": 28}, {"weight": 2, "random_weight": 0.1511146091675596, "id": 31}, {"weight": 1, "random_weight": 0.8743568463410547, "id": 34}], [{"weight": 2, "random_weight": 0.832166193067156, "id": 6}, {"weight": 1, "random_weight": 0.4706861807635312, "id": 8}, {"weight": 1, "random_weight": 0.070327472816895, "id": 9}, {"weight": 1, "random_weight": 0.9882719149022531, "id": 10}, {"weight": 3, "random_weight": 0.31572201321166504, "id": 16}, {"weight": 1, "random_weight": 0.582967593075494, "id": 28}, {"weight": 1, "random_weight": 0.20843450606953007, "id": 31}], [{"weight": 1, "random_weight": 0.5124740210977883, "id": 19}, {"weight": 2, "random_weight": 0.9063937419088589, "id": 23}, {"weight": 2, "random_weight": 0.1986423480910282, "id": 30}], [{"weight": 3, "random_weight": 0.9485402788417032, "id": 7}, {"weight": 1, "random_weight": 0.5124740210977883, "id": 18}, {"weight": 1, "random_weight": 0.6620263503486985, "id": 21}, {"weight": 1, "random_weight": 0.8858141853473676, "id": 26}, {"weight": 2, "random_weight": 0.3817005153967977, "id": 30}], [{"weight": 1, "random_weight": 0.26315996824837773, "id": 0}, {"weight": 2, "random_weight": 0.39955796829548706, "id": 1}, {"weight": 3, "random_weight": 0.5643316957933392, "id": 5}, {"weight": 2, "random_weight": 0.24062754124659058, "id": 11}, {"weight": 2, "random_weight": 0.45764961587193875, "id": 24}], [{"weight": 1, "random_weight": 0.03590374323551693, "id": 3}, {"weight": 3, "random_weight": 0.9461915250725256, "id": 7}, {"weight": 1, "random_weight": 0.6620263503486985, "id": 19}, {"weight": 1, "random_weight": 0.5778573311523025, "id": 25}, {"weight": 2, "random_weight": 0.8366019166408826, "id": 26}, {"weight": 2, "random_weight": 0.4154996169164402, "id": 35}], [{"weight": 1, "random_weight": 0.9035713597714097, "id": 2}, {"weight": 1, "random_weight": 0.710141350275285, "id": 16}, {"weight": 2, "random_weight": 0.79848797627411, "id": 25}, {"weight": 2, "random_weight": 0.275818065542495, "id": 34}], [{"weight": 1, "random_weight": 0.8780617888059121, "id": 12}, {"weight": 1, "random_weight": 0.3491118493690002, "id": 13}, {"weight": 2, "random_weight": 0.9063937419088589, "id": 18}, {"weight": 2, "random_weight": 0.6631354768047472, "id": 30}], [{"weight": 3, "random_weight": 0.6582864993963016, "id": 0}, {"weight": 1, "random_weight": 0.6711779246743013, "id": 5}, {"weight": 1, "random_weight": 0.09917156377274161, "id": 14}, {"weight": 2, "random_weight": 0.45764961587193875, "id": 20}, {"weight": 1, "random_weight": 0.3556268162713999, "id": 33}], [{"weight": 2, "random_weight": 0.5049388417188215, "id": 2}, {"weight": 2, "random_weight": 0.6844042563391108, "id": 3}, {"weight": 1, "random_weight": 0.5778573311523025, "id": 21}, {"weight": 2, "random_weight": 0.79848797627411, "id": 22}, {"weight": 1, "random_weight": 0.9266886816120795, "id": 34}, {"weight": 2, "random_weight": 0.7653660216643703, "id": 35}], [{"weight": 1, "random_weight": 0.8858141853473676, "id": 19}, {"weight": 2, "random_weight": 0.8366019166408826, "id": 21}, {"weight": 4, "random_weight": 0.5351419748471624, "id": 27}, {"weight": 2, "random_weight": 0.40708667932350506, "id": 32}, {"weight": 1, "random_weight": 0.980411462221032, "id": 35}], [{"weight": 2, "random_weight": 0.9844034943365504, "id": 15}, {"weight": 4, "random_weight": 0.5351419748471624, "id": 26}, {"weight": 2, "random_weight": 0.7035187304412196, "id": 29}, {"weight": 1, "random_weight": 0.6293424128084196, "id": 32}, {"weight": 1, "random_weight": 0.5066170401567114, "id": 35}], [{"weight": 2, "random_weight": 0.5718937828036534, "id": 16}, {"weight": 1, "random_weight": 0.582967593075494, "id": 17}, {"weight": 2, "random_weight": 0.4393488140162193, "id": 29}, {"weight": 3, "random_weight": 0.5555235445447746, "id": 34}], [{"weight": 2, "random_weight": 0.8771296230065246, "id": 6}, {"weight": 1, "random_weight": 0.9442834975864549, "id": 15}, {"weight": 2, "random_weight": 0.7035187304412196, "id": 27}, {"weight": 2, "random_weight": 0.4393488140162193, "id": 28}, {"weight": 1, "random_weight": 0.824788471929904, "id": 35}], [{"weight": 1, "random_weight": 0.8748375371843705, "id": 12}, {"weight": 2, "random_weight": 0.1986423480910282, "id": 18}, {"weight": 2, "random_weight": 0.3817005153967977, "id": 19}, {"weight": 2, "random_weight": 0.6631354768047472, "id": 23}, {"weight": 1, "random_weight": 0.875508952759541, "id": 32}], [{"weight": 3, "random_weight": 0.141721576501454, "id": 9}, {"weight": 2, "random_weight": 0.1511146091675596, "id": 16}, {"weight": 1, "random_weight": 0.20843450606953007, "id": 17}], [{"weight": 3, "random_weight": 0.020320598347317365, "id": 12}, {"weight": 1, "random_weight": 0.7710053811101878, "id": 13}, {"weight": 2, "random_weight": 0.40708667932350506, "id": 26}, {"weight": 1, "random_weight": 0.6293424128084196, "id": 27}, {"weight": 1, "random_weight": 0.875508952759541, "id": 30}, {"weight": 2, "random_weight": 0.9684350188275207, "id": 33}], [{"weight": 1, "random_weight": 0.5108609937833836, "id": 5}, {"weight": 2, "random_weight": 0.946408708218907, "id": 14}, {"weight": 2, "random_weight": 0.6718142979905276, "id": 15}, {"weight": 1, "random_weight": 0.3556268162713999, "id": 24}, {"weight": 2, "random_weight": 0.9684350188275207, "id": 32}], [{"weight": 1, "random_weight": 0.8743568463410547, "id": 16}, {"weight": 2, "random_weight": 0.275818065542495, "id": 22}, {"weight": 1, "random_weight": 0.9266886816120795, "id": 25}, {"weight": 3, "random_weight": 0.5555235445447746, "id": 28}, {"weight": 3, "random_weight": 0.8614792709658355, "id": 35}], [{"weight": 2, "random_weight": 0.4154996169164402, "id": 21}, {"weight": 2, "random_weight": 0.7653660216643703, "id": 25}, {"weight": 1, "random_weight": 0.980411462221032, "id": 26}, {"weight": 1, "random_weight": 0.5066170401567114, "id": 27}, {"weight": 1, "random_weight": 0.824788471929904, "id": 29}, {"weight": 3, "random_weight": 0.8614792709658355, "id": 34}]]}