{"directed": false, "multigraph": false, "graph": [], "nodes": [{"graph": null, "nnodes": 4, "nedges": 4, "density": 0.6666666666666666, "atomics": "[16, 3, 4, 15]", "group_pop": 4, "init_part_assignment": 3, "id": 0}, {"graph": null, "nnodes": 4, "nedges": 4, "density": 0.6666666666666666, "atomics": "[17, 18, 5, 6]", "group_pop": 4, "init_part_assignment": 3, "id": 1}, {"graph": null, "nnodes": 4, "nedges": 3, "density": 0.5, "atomics": "[89, 90, 102, 103]", "group_pop": 4, "init_part_assignment": 6, "id": 2}, {"graph": null, "nnodes": 4, "nedges": 3, "density": 0.5, "atomics": "[91, 77, 78, 79]", "group_pop": 4, "init_part_assignment": 5, "id": 3}, {"graph": null, "nnodes": 4, "nedges": 4, "density": 0.6666666666666666, "atomics": "[8, 19, 20, 7]", "group_pop": 4, "init_part_assignment": 3, "id": 4}, {"graph": null, "nnodes": 4, "nedges": 3, "density": 0.5, "atomics": "[9, 34, 21, 33]", "group_pop": 4, "init_part_assignment": 1, "id": 5}, {"graph": null, "nnodes": 4, "nedges": 4, "density": 0.6666666666666666, "atomics": "[120, 121, 132, 133]", "group_pop": 4, "init_part_assignment": 9, "id": 6}, {"graph": null, "nnodes": 4, "nedges": 4, "density": 0.6666666666666666, "atomics": "[122, 123, 134, 135]", "group_pop": 4, "init_part_assignment": 2, "id": 7}, {"graph": null, "nnodes": 4, "nedges": 4, "density": 0.6666666666666666, "atomics": "[96, 97, 108, 109]", "group_pop": 4, "init_part_assignment": 9, "id": 8}, {"graph": null, "nnodes": 4, "nedges": 3, "density": 0.5, "atomics": "[98, 110, 86, 87]", "group_pop": 4, "init_part_assignment": 10, "id": 9}, {"graph": null, "nnodes": 4, "nedges": 3, "density": 0.5, "atomics": "[49, 50, 60, 61]", "group_pop": 4, "init_part_assignment": 11, "id": 10}, {"graph": null, "nnodes": 4, "nedges": 3, "density": 0.5, "atomics": "[51, 27, 38, 39]", "group_pop": 4, "init_part_assignment": 11, "id": 11}, {"graph": null, "nnodes": 4, "nedges": 3, "density": 0.5, "atomics": "[64, 52, 62, 63]", "group_pop": 4, "init_part_assignment": 11, "id": 12}, {"graph": null, "nnodes": 4, "nedges": 4, "density": 0.6666666666666666, "atomics": "[136, 137, 124, 125]", "group_pop": 4, "init_part_assignment": 2, "id": 13}, {"graph": null, "nnodes": 4, "nedges": 4, "density": 0.6666666666666666, "atomics": "[138, 139, 126, 127]", "group_pop": 4, "init_part_assignment": 2, "id": 14}, {"graph": null, "nnodes": 4, "nedges": 4, "density": 0.6666666666666666, "atomics": "[130, 131, 142, 143]", "group_pop": 4, "init_part_assignment": 0, "id": 15}, {"graph": null, "nnodes": 4, "nedges": 3, "density": 0.5, "atomics": "[58, 68, 69, 70]", "group_pop": 4, "init_part_assignment": 4, "id": 16}, {"graph": null, "nnodes": 4, "nedges": 3, "density": 0.5, "atomics": "[59, 35, 47, 71]", "group_pop": 4, "init_part_assignment": 1, "id": 17}, {"graph": null, "nnodes": 4, "nedges": 3, "density": 0.5, "atomics": "[32, 44, 45, 46]", "group_pop": 4, "init_part_assignment": 4, "id": 18}, {"graph": null, "nnodes": 4, "nedges": 4, "density": 0.6666666666666666, "atomics": "[40, 41, 28, 29]", "group_pop": 4, "init_part_assignment": 8, "id": 19}, {"graph": null, "nnodes": 4, "nedges": 3, "density": 0.5, "atomics": "[128, 105, 104, 116]", "group_pop": 4, "init_part_assignment": 6, "id": 20}, {"graph": null, "nnodes": 4, "nedges": 3, "density": 0.5, "atomics": "[129, 140, 117, 141]", "group_pop": 4, "init_part_assignment": 0, "id": 21}, {"graph": null, "nnodes": 4, "nedges": 3, "density": 0.5, "atomics": "[24, 48, 36, 37]", "group_pop": 4, "init_part_assignment": 7, "id": 22}, {"graph": null, "nnodes": 4, "nedges": 3, "density": 0.5, "atomics": "[0, 1, 2, 12]", "group_pop": 4, "init_part_assignment": 7, "id": 23}, {"graph": null, "nnodes": 4, "nedges": 4, "density": 0.6666666666666666, "atomics": "[42, 43, 30, 31]", "group_pop": 4, "init_part_assignment": 8, "id": 24}, {"graph": null, "nnodes": 4, "nedges": 4, "density": 0.6666666666666666, "atomics": "[10, 11, 22, 23]", "group_pop": 4, "init_part_assignment": 1, "id": 25}, {"graph": null, "nnodes": 4, "nedges": 4, "density": 0.6666666666666666, "atomics": "[72, 73, 84, 85]", "group_pop": 4, "init_part_assignment": 9, "id": 26}, {"graph": null, "nnodes": 4, "nedges": 4, "density": 0.6666666666666666, "atomics": "[106, 107, 118, 119]", "group_pop": 4, "init_part_assignment": 0, "id": 27}, {"graph": null, "nnodes": 4, "nedges": 4, "density": 0.6666666666666666, "atomics": "[82, 83, 94, 95]", "group_pop": 4, "init_part_assignment": 4, "id": 28}, {"graph": null, "nnodes": 4, "nedges": 4, "density": 0.6666666666666666, "atomics": "[25, 26, 13, 14]", "group_pop": 4, "init_part_assignment": 7, "id": 29}, {"graph": null, "nnodes": 4, "nedges": 3, "density": 0.5, "atomics": "[56, 57, 67, 55]", "group_pop": 4, "init_part_assignment": 5, "id": 30}, {"graph": null, "nnodes": 4, "nedges": 4, "density": 0.6666666666666666, "atomics": "[80, 81, 92, 93]", "group_pop": 4, "init_part_assignment": 5, "id": 31}, {"graph": null, "nnodes": 4, "nedges": 4, "density": 0.6666666666666666, "atomics": "[65, 66, 53, 54]", "group_pop": 4, "init_part_assignment": 8, "id": 32}, {"graph": null, "nnodes": 4, "nedges": 3, "density": 0.5, "atomics": "[88, 74, 75, 76]", "group_pop": 4, "init_part_assignment": 10, "id": 33}, {"graph": null, "nnodes": 4, "nedges": 3, "density": 0.5, "atomics": "[113, 114, 115, 101]", "group_pop": 4, "init_part_assignment": 6, "id": 34}, {"graph": null, "nnodes": 4, "nedges": 4, "density": 0.6666666666666666, "atomics": "[112, 99, 100, 111]", "group_pop": 4, "init_part_assignment": 10, "id": 35}], "adjacency": [[{"weight": 2, "random_weight": 0.34888350410948965, "id": 1}, {"weight": 1, "random_weight": 0.9953563736203977, "id": 11}, {"weight": 1, "random_weight": 0.6365205329815861, "id": 19}, {"weight": 1, "random_weight": 0.9729862307214118, "id": 23}, {"weight": 1, "random_weight": 0.8422351022174808, "id": 29}], [{"weight": 2, "random_weight": 0.34888350410948965, "id": 0}, {"weight": 2, "random_weight": 0.22875251851962075, "id": 4}, {"weight": 1, "random_weight": 0.07078177540535713, "id": 19}, {"weight": 1, "random_weight": 0.8677056759318187, "id": 24}], [{"weight": 4, "random_weight": 0.4807067863045891, "id": 3}, {"weight": 1, "random_weight": 0.2693057482870337, "id": 20}, {"weight": 1, "random_weight": 0.8463512691932822, "id": 33}, {"weight": 4, "random_weight": 0.26567485705503646, "id": 34}], [{"weight": 4, "random_weight": 0.4807067863045891, "id": 2}, {"weight": 1, "random_weight": 0.1650564982440086, "id": 30}, {"weight": 2, "random_weight": 0.06500602401552646, "id": 31}, {"weight": 2, "random_weight": 0.4543737697318583, "id": 32}, {"weight": 1, "random_weight": 0.7057629904690859, "id": 33}], [{"weight": 2, "random_weight": 0.22875251851962075, "id": 1}, {"weight": 2, "random_weight": 0.42467613490857314, "id": 5}, {"weight": 1, "random_weight": 0.9865079845033229, "id": 18}, {"weight": 1, "random_weight": 0.9398404427805269, "id": 24}], [{"weight": 2, "random_weight": 0.42467613490857314, "id": 4}, {"weight": 1, "random_weight": 0.3858298771787978, "id": 17}, {"weight": 3, "random_weight": 0.8531759989683907, "id": 18}, {"weight": 3, "random_weight": 0.44267264410282925, "id": 25}], [{"weight": 2, "random_weight": 0.3599367390677244, "id": 7}, {"weight": 2, "random_weight": 0.23334681183243466, "id": 8}], [{"weight": 2, "random_weight": 0.3599367390677244, "id": 6}, {"weight": 1, "random_weight": 0.5351917799972649, "id": 9}, {"weight": 2, "random_weight": 0.010055397596110738, "id": 13}, {"weight": 1, "random_weight": 0.41480501673005454, "id": 35}], [{"weight": 2, "random_weight": 0.23334681183243466, "id": 6}, {"weight": 2, "random_weight": 0.9006650248939597, "id": 9}, {"weight": 2, "random_weight": 0.41268649167830784, "id": 26}], [{"weight": 1, "random_weight": 0.5351917799972649, "id": 7}, {"weight": 2, "random_weight": 0.9006650248939597, "id": 8}, {"weight": 1, "random_weight": 0.6897756539123444, "id": 26}, {"weight": 3, "random_weight": 0.15022259657193826, "id": 33}, {"weight": 3, "random_weight": 0.39476138384996284, "id": 35}], [{"weight": 2, "random_weight": 0.672105223064802, "id": 11}, {"weight": 2, "random_weight": 0.43137181565471383, "id": 12}, {"weight": 3, "random_weight": 0.5703696822106145, "id": 22}, {"weight": 2, "random_weight": 0.06363118379543997, "id": 26}], [{"weight": 1, "random_weight": 0.9953563736203977, "id": 0}, {"weight": 2, "random_weight": 0.672105223064802, "id": 10}, {"weight": 2, "random_weight": 0.0967629283145991, "id": 12}, {"weight": 2, "random_weight": 0.9109648715963286, "id": 19}, {"weight": 1, "random_weight": 0.6869363269649773, "id": 22}, {"weight": 2, "random_weight": 0.4613738851242102, "id": 29}], [{"weight": 2, "random_weight": 0.43137181565471383, "id": 10}, {"weight": 2, "random_weight": 0.0967629283145991, "id": 11}, {"weight": 1, "random_weight": 0.5438666651348276, "id": 19}, {"weight": 2, "random_weight": 0.5958841577565989, "id": 32}, {"weight": 3, "random_weight": 0.5142191600834333, "id": 33}], [{"weight": 2, "random_weight": 0.010055397596110738, "id": 7}, {"weight": 2, "random_weight": 0.5432472545214517, "id": 14}, {"weight": 1, "random_weight": 0.9315595087447728, "id": 34}, {"weight": 1, "random_weight": 0.14359433626344342, "id": 35}], [{"weight": 2, "random_weight": 0.5432472545214517, "id": 13}, {"weight": 1, "random_weight": 0.7041872376408826, "id": 20}, {"weight": 1, "random_weight": 0.050892137740824794, "id": 21}, {"weight": 2, "random_weight": 0.7450672495114614, "id": 34}], [{"weight": 2, "random_weight": 0.14798395860142133, "id": 21}, {"weight": 2, "random_weight": 0.636690589988816, "id": 27}], [{"weight": 2, "random_weight": 0.7194975334091528, "id": 17}, {"weight": 1, "random_weight": 0.10044996823201058, "id": 18}, {"weight": 1, "random_weight": 0.23249606542459977, "id": 28}, {"weight": 4, "random_weight": 0.21345739948832188, "id": 30}, {"weight": 2, "random_weight": 0.5464252104598873, "id": 31}], [{"weight": 1, "random_weight": 0.3858298771787978, "id": 5}, {"weight": 2, "random_weight": 0.7194975334091528, "id": 16}, {"weight": 1, "random_weight": 0.1379706282999088, "id": 18}, {"weight": 1, "random_weight": 0.9604197917741941, "id": 25}, {"weight": 1, "random_weight": 0.9111399414987209, "id": 28}], [{"weight": 1, "random_weight": 0.9865079845033229, "id": 4}, {"weight": 3, "random_weight": 0.8531759989683907, "id": 5}, {"weight": 1, "random_weight": 0.10044996823201058, "id": 16}, {"weight": 1, "random_weight": 0.1379706282999088, "id": 17}, {"weight": 2, "random_weight": 0.8282396430706059, "id": 24}, {"weight": 2, "random_weight": 0.22034730035873684, "id": 30}], [{"weight": 1, "random_weight": 0.6365205329815861, "id": 0}, {"weight": 1, "random_weight": 0.07078177540535713, "id": 1}, {"weight": 2, "random_weight": 0.9109648715963286, "id": 11}, {"weight": 1, "random_weight": 0.5438666651348276, "id": 12}, {"weight": 2, "random_weight": 0.9805462593032616, "id": 24}, {"weight": 1, "random_weight": 0.46595304212062916, "id": 32}], [{"weight": 1, "random_weight": 0.2693057482870337, "id": 2}, {"weight": 1, "random_weight": 0.7041872376408826, "id": 14}, {"weight": 4, "random_weight": 0.6404346496448367, "id": 21}, {"weight": 1, "random_weight": 0.45980481706943965, "id": 27}, {"weight": 2, "random_weight": 0.20367257281848616, "id": 31}, {"weight": 1, "random_weight": 0.9762893129294944, "id": 34}], [{"weight": 1, "random_weight": 0.050892137740824794, "id": 14}, {"weight": 2, "random_weight": 0.14798395860142133, "id": 15}, {"weight": 4, "random_weight": 0.6404346496448367, "id": 20}, {"weight": 1, "random_weight": 0.273366336021464, "id": 27}], [{"weight": 3, "random_weight": 0.5703696822106145, "id": 10}, {"weight": 1, "random_weight": 0.6869363269649773, "id": 11}, {"weight": 1, "random_weight": 0.7747571746653694, "id": 23}, {"weight": 2, "random_weight": 0.5181173304208064, "id": 29}], [{"weight": 1, "random_weight": 0.9729862307214118, "id": 0}, {"weight": 1, "random_weight": 0.7747571746653694, "id": 22}, {"weight": 3, "random_weight": 0.8859475242163838, "id": 29}], [{"weight": 1, "random_weight": 0.8677056759318187, "id": 1}, {"weight": 1, "random_weight": 0.9398404427805269, "id": 4}, {"weight": 2, "random_weight": 0.8282396430706059, "id": 18}, {"weight": 2, "random_weight": 0.9805462593032616, "id": 19}, {"weight": 1, "random_weight": 0.39020598455235544, "id": 30}, {"weight": 1, "random_weight": 0.2143691267559673, "id": 32}], [{"weight": 3, "random_weight": 0.44267264410282925, "id": 5}, {"weight": 1, "random_weight": 0.9604197917741941, "id": 17}], [{"weight": 2, "random_weight": 0.41268649167830784, "id": 8}, {"weight": 1, "random_weight": 0.6897756539123444, "id": 9}, {"weight": 2, "random_weight": 0.06363118379543997, "id": 10}, {"weight": 1, "random_weight": 0.9247796903065862, "id": 33}], [{"weight": 2, "random_weight": 0.636690589988816, "id": 15}, {"weight": 1, "random_weight": 0.45980481706943965, "id": 20}, {"weight": 1, "random_weight": 0.273366336021464, "id": 21}, {"weight": 2, "random_weight": 0.8699173773282255, "id": 28}], [{"weight": 1, "random_weight": 0.23249606542459977, "id": 16}, {"weight": 1, "random_weight": 0.9111399414987209, "id": 17}, {"weight": 2, "random_weight": 0.8699173773282255, "id": 27}, {"weight": 2, "random_weight": 0.9612836594896155, "id": 31}], [{"weight": 1, "random_weight": 0.8422351022174808, "id": 0}, {"weight": 2, "random_weight": 0.4613738851242102, "id": 11}, {"weight": 2, "random_weight": 0.5181173304208064, "id": 22}, {"weight": 3, "random_weight": 0.8859475242163838, "id": 23}], [{"weight": 1, "random_weight": 0.1650564982440086, "id": 3}, {"weight": 4, "random_weight": 0.21345739948832188, "id": 16}, {"weight": 2, "random_weight": 0.22034730035873684, "id": 18}, {"weight": 1, "random_weight": 0.39020598455235544, "id": 24}, {"weight": 2, "random_weight": 0.6227634213539684, "id": 32}], [{"weight": 2, "random_weight": 0.06500602401552646, "id": 3}, {"weight": 2, "random_weight": 0.5464252104598873, "id": 16}, {"weight": 2, "random_weight": 0.20367257281848616, "id": 20}, {"weight": 2, "random_weight": 0.9612836594896155, "id": 28}], [{"weight": 2, "random_weight": 0.4543737697318583, "id": 3}, {"weight": 2, "random_weight": 0.5958841577565989, "id": 12}, {"weight": 1, "random_weight": 0.46595304212062916, "id": 19}, {"weight": 1, "random_weight": 0.2143691267559673, "id": 24}, {"weight": 2, "random_weight": 0.6227634213539684, "id": 30}], [{"weight": 1, "random_weight": 0.8463512691932822, "id": 2}, {"weight": 1, "random_weight": 0.7057629904690859, "id": 3}, {"weight": 3, "random_weight": 0.15022259657193826, "id": 9}, {"weight": 3, "random_weight": 0.5142191600834333, "id": 12}, {"weight": 1, "random_weight": 0.9247796903065862, "id": 26}, {"weight": 1, "random_weight": 0.9428161250162056, "id": 35}], [{"weight": 4, "random_weight": 0.26567485705503646, "id": 2}, {"weight": 1, "random_weight": 0.9315595087447728, "id": 13}, {"weight": 2, "random_weight": 0.7450672495114614, "id": 14}, {"weight": 1, "random_weight": 0.9762893129294944, "id": 20}, {"weight": 2, "random_weight": 0.11552873617456116, "id": 35}], [{"weight": 1, "random_weight": 0.41480501673005454, "id": 7}, {"weight": 3, "random_weight": 0.39476138384996284, "id": 9}, {"weight": 1, "random_weight": 0.14359433626344342, "id": 13}, {"weight": 1, "random_weight": 0.9428161250162056, "id": 33}, {"weight": 2, "random_weight": 0.11552873617456116, "id": 34}]]}